COPYING
COPYING.LESSER
MANIFEST.in
README.rst
requirements-sphinx.txt
requirements.txt
setup.py
Biggus.egg-info/PKG-INFO
Biggus.egg-info/SOURCES.txt
Biggus.egg-info/dependency_links.txt
Biggus.egg-info/top_level.txt
biggus/__init__.py
biggus/_init.py
biggus/tests/__init__.py
biggus/tests/test_adapter.py
biggus/tests/test_aggregation.py
biggus/tests/test_array.py
biggus/tests/test_elementwise.py
biggus/tests/test_integration.py
biggus/tests/test_linear_mosaic.py
biggus/tests/test_ndarray.py
biggus/tests/test_pep8.py
biggus/tests/test_save.py
biggus/tests/test_stack.py
biggus/tests/integration/__init__.py
biggus/tests/integration/test_aggregation.py
biggus/tests/integration/test_engine.py
biggus/tests/integration/test_maths.py
biggus/tests/unit/__init__.py
biggus/tests/unit/init/__init__.py
biggus/tests/unit/init/_aggregation_test_framework.py
biggus/tests/unit/init/test_Array.py
biggus/tests/unit/init/test_ArrayContainer.py
biggus/tests/unit/init/test_ArrayStack.py
biggus/tests/unit/init/test_AsDataTypeArray.py
biggus/tests/unit/init/test_BroadcastArray.py
biggus/tests/unit/init/test_ConstantArray.py
biggus/tests/unit/init/test_LinearMosaic.py
biggus/tests/unit/init/test_MaskValueArray.py
biggus/tests/unit/init/test_NewAxesArray.py
biggus/tests/unit/init/test_NumpyArrayAdapter.py
biggus/tests/unit/init/test_TransposedArray.py
biggus/tests/unit/init/test__ArrayAdapter.py
biggus/tests/unit/init/test__Elementwise.py
biggus/tests/unit/init/test__all_slices.py
biggus/tests/unit/init/test__dual_input_fn_wrapper.py
biggus/tests/unit/init/test__full_keys.py
biggus/tests/unit/init/test__normalise_axis.py
biggus/tests/unit/init/test__sliced_shape.py
biggus/tests/unit/init/test__ufunc_wrapper.py
biggus/tests/unit/init/test__unary_fn_wrapper.py
biggus/tests/unit/init/test_count.py
biggus/tests/unit/init/test_ensure_array.py
biggus/tests/unit/init/test_max.py
biggus/tests/unit/init/test_mean.py
biggus/tests/unit/init/test_min.py
biggus/tests/unit/init/test_ones.py
biggus/tests/unit/init/test_size.py
biggus/tests/unit/init/test_std_var.py
biggus/tests/unit/init/test_sum.py
