Metadata-Version: 1.1
Name: Biggus
Version: 0.14.0
Summary: Virtual large arrays and lazy evaluation
Home-page: https://github.com/SciTools/biggus
Author: Richard Hattersley
Author-email: rhattersley@gmail.com
License: UNKNOWN
Platform: UNKNOWN
Classifier: License :: OSI Approved :: GNU Lesser General Public License v3 (LGPLv3)
Classifier: Programming Language :: Python :: 2
Classifier: Programming Language :: Python :: 2.7
Classifier: Programming Language :: Python :: 3
Classifier: Programming Language :: Python :: 3.3
Classifier: Programming Language :: Python :: 3.4
Classifier: Programming Language :: Python :: 3.5
